SyncAsync/__init__.py
SyncAsync/core.py
sync_async_api-0.1.0.dist-info/METADATA
sync_async_api-0.1.0.dist-info/WHEEL
sync_async_api-0.1.0.dist-info/RECORD
