Metadata-Version: 2.1
Name: sync-async-api
Version: 0.1.0
Summary: Interface for easy access to asynchrneous methods for synchroneous users
License: MIT
Keywords: asynchrneous,api,IPython,accessibility
Author: Tobias Duewell
Author-email: dev@duewell.ch
Requires-Python: >=3.11,<4.0
Classifier: License :: OSI Approved :: MIT License
Classifier: Programming Language :: Python :: 3
Classifier: Programming Language :: Python :: 3.11
